klepto/__info__.py
klepto/__init__.py
klepto/_abc.py
klepto/_archives.py
klepto/_cache.py
klepto/_inspect.py
klepto/_pickle.py
klepto/archives.py
klepto/crypto.py
klepto/keymaps.py
klepto/rounding.py
klepto/safe.py
klepto/tools.py
klepto/tests/__init__.py
klepto/tests/__main__.py
klepto/tests/cleanup_basic.py
klepto/tests/test_alchemy.py
klepto/tests/test_basic.py
klepto/tests/test_bigdata.py
klepto/tests/test_cache.py
klepto/tests/test_cache_info.py
klepto/tests/test_cachekeys.py
klepto/tests/test_chaining.py
klepto/tests/test_crypto.py
klepto/tests/test_frame.py
klepto/tests/test_hdf.py
klepto/tests/test_ignore.py
klepto/tests/test_keymaps.py
klepto/tests/test_pickles.py
klepto/tests/test_readwrite.py
klepto/tests/test_rounding.py
klepto/tests/test_validate.py
klepto/tests/test_workflow.py
klepto-0.2.8.dist-info/LICENSE
klepto-0.2.8.dist-info/METADATA
klepto-0.2.8.dist-info/WHEEL
klepto-0.2.8.dist-info/top_level.txt
klepto-0.2.8.dist-info/RECORD
