Metadata-Version: 2.1
Name: klepto
Version: 0.2.8
Summary: persistent caching to memory, disk, or database
Home-page: https://github.com/uqfoundation/klepto
Download-URL: https://pypi.org/project/klepto/#files
Author: Mike McKerns
Author-email: mmckerns@uqfoundation.org
Maintainer: Mike McKerns
Maintainer-email: mmckerns@uqfoundation.org
License: BSD-3-Clause
Project-URL: Documentation, http://klepto.rtfd.io
Project-URL: Source Code, https://github.com/uqfoundation/klepto
Project-URL: Bug Tracker, https://github.com/uqfoundation/klepto/issues
Platform: Linux
Platform: Windows
Platform: Mac
Classifier: Development Status :: 5 - Production/Stable
Classifier: Intended Audience :: Developers
Classifier: Intended Audience :: Science/Research
Classifier: License :: OSI Approved :: BSD License
Classifier: Programming Language :: Python :: 3
Classifier: Programming Language :: Python :: 3.9
Classifier: Programming Language :: Python :: 3.10
Classifier: Programming Language :: Python :: 3.11
Classifier: Programming Language :: Python :: 3.12
Classifier: Programming Language :: Python :: 3.13
Classifier: Programming Language :: Python :: 3.14
Classifier: Programming Language :: Python :: Implementation :: CPython
Classifier: Programming Language :: Python :: Implementation :: PyPy
Classifier: Topic :: Database
Classifier: Topic :: Scientific/Engineering
Classifier: Topic :: Software Development
Requires-Python: >=3.9
License-File: LICENSE
Requires-Dist: pox>=0.3.7
Requires-Dist: dill>=0.4.1
Provides-Extra: archives
Requires-Dist: h5py>=2.8.0; extra == "archives"
Requires-Dist: sqlalchemy>=1.4.0; extra == "archives"
Requires-Dist: pandas>=0.17.0; extra == "archives"
Provides-Extra: crypto
Requires-Dist: jsonpickle>=0.9.6; extra == "crypto"
Requires-Dist: cloudpickle>=0.5.2; extra == "crypto"
